{
  "clientChanges": {
    "departedClient": "Client 1 uscito",
    "arrivedClient": "Client 13 -\u003e NodoFog 2"
  },
  "clients": [
    {
      "arrivalTime": 0,
      "id": 2,
      "totalRequiredTime": 937,
      "queueTime": 48
    },
    {
      "arrivalTime": 0,
      "id": 5,
      "totalRequiredTime": 1018,
      "queueTime": 26
    },
    {
      "arrivalTime": 0,
      "id": 8,
      "totalRequiredTime": 605,
      "queueTime": 40
    },
    {
      "arrivalTime": 0,
      "id": 9,
      "totalRequiredTime": 801,
      "queueTime": 21
    },
    {
      "arrivalTime": 0,
      "id": 10,
      "totalRequiredTime": 1189,
      "queueTime": 56
    },
    {
      "arrivalTime": 2,
      "id": 11,
      "totalRequiredTime": 637,
      "queueTime": 30
    },
    {
      "arrivalTime": 3,
      "id": 12,
      "totalRequiredTime": 769,
      "queueTime": 47
    },
    {
      "arrivalTime": 7,
      "id": 13,
      "totalRequiredTime": 153,
      "queueTime": 10
    }
  ],
  "totalClients": 8,
  "totalSwaps:": 0,
  "nodi": [
    {
      "totalExecutionTime": 70,
      "maxCapacity": 2,
      "totalServices": 8,
      "id": 1,
      "computationCapability": 68,
      "totalDelay": 9
    },
    {
      "totalExecutionTime": 125,
      "maxCapacity": 4,
      "totalServices": 19,
      "id": 2,
      "computationCapability": 66,
      "totalDelay": 37
    },
    {
      "totalExecutionTime": 155,
      "maxCapacity": 4,
      "totalServices": 17,
      "id": 3,
      "computationCapability": 46,
      "totalDelay": 66
    },
    {
      "totalExecutionTime": 110,
      "maxCapacity": 3,
      "totalServices": 8,
      "id": 4,
      "computationCapability": 46,
      "totalDelay": 50
    },
    {
      "totalExecutionTime": 109,
      "maxCapacity": 5,
      "totalServices": 15,
      "id": 5,
      "computationCapability": 41,
      "totalDelay": 26
    }
  ],
  "timeSlot": 9,
  "totalNodiFog": 5,
  "timeSlotDuration": 10,
  "matching": {
    "Client 2": "NodoFog 1",
    "Client 13": "NodoFog 2",
    "Client 12": "NodoFog 2",
    "Client 11": "NodoFog 3",
    "Client 10": "NodoFog 3",
    "Client 9": "NodoFog 2",
    "Client 8": "NodoFog 5",
    "Client 5": "NodoFog 4"
  }
}